turbotape/__init__.py
turbotape/cache.py
turbotape/cli.py
turbotape/dataframe.py
turbotape/helpers.py
turbotape/records.py
turbotape/session.py
turbotape-0.0.10.dist-info/METADATA
turbotape-0.0.10.dist-info/WHEEL
turbotape-0.0.10.dist-info/licenses/LICENSE
turbotape-0.0.10.dist-info/RECORD
