Metadata-Version: 2.4
Name: turbotape
Version: 0.0.10
Summary: A utility package for using the public API of tapeapp.com with Python.
Project-URL: Homepage, https://github.com/uwekamper/turbotape
Project-URL: Issues, https://github.com/uwekamper/turbotape/issues
Author-email: Uwe Kamper <me@uwekamper.de>
License-File: LICENSE
Classifier: License :: OSI Approved :: MIT License
Classifier: Operating System :: OS Independent
Classifier: Programming Language :: Python :: 3
Requires-Python: >=3.8
Requires-Dist: python-dateutil
Requires-Dist: requests
